ofxstatement_sparkasse_freiburg-0.0.3-py3.5-nspkg.pth
ofxstatement/plugins/germany_sparkasse_freiburg.py
ofxstatement_sparkasse_freiburg-0.0.3.dist-info/METADATA
ofxstatement_sparkasse_freiburg-0.0.3.dist-info/RECORD
ofxstatement_sparkasse_freiburg-0.0.3.dist-info/WHEEL
ofxstatement_sparkasse_freiburg-0.0.3.dist-info/entry_points.txt
ofxstatement_sparkasse_freiburg-0.0.3.dist-info/namespace_packages.txt
ofxstatement_sparkasse_freiburg-0.0.3.dist-info/top_level.txt
ofxstatement_sparkasse_freiburg-0.0.3.dist-info/zip-safe
