Metadata-Version: 2.1
Name: ofxstatement-sparkasse-freiburg
Version: 0.0.3
Summary: ofxstatement plugin for German bank Sparkasse Freiburg-Nördlicher Breisgau
Home-page: https://github.com/omarkohl/ofxstatement-sparkasse-freiburg
Author: Omar Kohl
Author-email: omarkohl@gmail.com
License: MIT
Keywords: ofx,banking,statement
Platform: UNKNOWN
Classifier: Development Status :: 3 - Alpha
Classifier: Programming Language :: Python :: 3
Classifier: Natural Language :: English
Classifier: Topic :: Office/Business :: Financial :: Accounting
Classifier: Topic :: Utilities
Classifier: Environment :: Console
Classifier: Operating System :: OS Independent
Classifier: License :: OSI Approved :: MIT License
Requires-Dist: ofxstatement
